{
  "company_name": "Mizick Miller & Company, Inc.",
  "role_title": "Staff Accountant",
  "employment_type": null,
  "about_the_company": "Mizick Miller & Company, Inc. offers payroll, accounting, business consulting, agri-business consulting, and tax services to businesses, organizations, and individuals.",
  "job_responsibilities": [
    "Provide accounting services",
    "Handle payroll processing",
    "Offer business consulting",
    "Provide agri-business consulting",
    "Assist with tax services",
    "Work in a fast-paced environment",
    "Meet strict deadlines"
  ],
  "required_hard_skills": [
    "Microsoft Office Suite"
  ],
  "required_soft_skills": [
    "Attention to detail",
    "Written communication",
    "Oral communication",
    "Teamwork",
    "Professionalism"
  ],
  "required_language_proficiencies": [
    "English"
  ],
  "required_education": "2- or 4-year degree, or equivalent experience",
  "required_work_authorization": null,
  "job_location": "Crawford & Wyandot counties, Ohio",
  "certifications": []
}